<?xml version="1.0" encoding="UTF-8"?>
<Tokens version="1.0">
	<File path="Classes/USMonetizationPurchaseInfo.html">
		
		<Token>
			<TokenIdentifier>//apple_ref/occ/cl/USMonetizationPurchaseInfo</TokenIdentifier>
			<Abstract type="html">A specialization of USPurchaseInfo that provides initializers appropriate for use when
creating USMonetizationEvent objects.</Abstract>
			<DeclaredIn>USMonetizationPurchaseInfo.h</DeclaredIn>
            
			
			<NodeRef refid="9"/>
		</Token>
		
		
		<Token>
			<TokenIdentifier>//apple_ref/occ/clm/USMonetizationPurchaseInfo/infoWithResolution:totalPrice:currency:product:</TokenIdentifier>
			<Abstract type="html">Convenience method for creating monetization information object.</Abstract>
			<DeclaredIn>USMonetizationPurchaseInfo.h</DeclaredIn>
			
			<Declaration>+ (instancetype)infoWithResolution:(USPurchaseResolution)resolution totalPrice:(float)totalPrice currency:(NSString *)currency product:(NSString *)product</Declaration>
			<Parameters>
				<Parameter>
					<Name>resolution</Name>
					<Abstract type="html">Represents type of monetary transaction that took place. Refer to the
USPurchaseResolution enumeration or more details.</Abstract>
				</Parameter><Parameter>
					<Name>totalPrice</Name>
					<Abstract type="html">The total price of the transaction, including fractional amounts of the currency, before
store fees have been taken into account.</Abstract>
				</Parameter><Parameter>
					<Name>currency</Name>
					<Abstract type="html">The currency as a 3-character ISO 4217 code.</Abstract>
				</Parameter><Parameter>
					<Name>product</Name>
					<Abstract type="html">Unique identifier of the product.</Abstract>
				</Parameter>
			</Parameters>
			
			<Anchor>//api/name/infoWithResolution:totalPrice:currency:product:</Anchor>
            <NodeRef refid="9"/>
		</Token>
		
		<Token>
			<TokenIdentifier>//apple_ref/occ/clm/USMonetizationPurchaseInfo/infoWithResolution:currency:quantity:product:price:</TokenIdentifier>
			<Abstract type="html">Convenience method for creating monetization information object. The total price for the
transaction is calculated internally by multiplying the quantity and unit price.</Abstract>
			<DeclaredIn>USMonetizationPurchaseInfo.h</DeclaredIn>
			
			<Declaration>+ (instancetype)infoWithResolution:(USPurchaseResolution)resolution currency:(NSString *)currency quantity:(NSUInteger)quantity product:(NSString *)product price:(float)price</Declaration>
			<Parameters>
				<Parameter>
					<Name>resolution</Name>
					<Abstract type="html">Represents type of monetary transaction that took place. Refer to the
USPurchaseResolution enumeration or more details.</Abstract>
				</Parameter><Parameter>
					<Name>currency</Name>
					<Abstract type="html">The currency as a 3-character ISO 4217 code.</Abstract>
				</Parameter><Parameter>
					<Name>quantity</Name>
					<Abstract type="html">The number of goods purchased.</Abstract>
				</Parameter><Parameter>
					<Name>product</Name>
					<Abstract type="html">Unique identifier of the product.</Abstract>
				</Parameter><Parameter>
					<Name>price</Name>
					<Abstract type="html">The price per unit in local currency.</Abstract>
				</Parameter>
			</Parameters>
			
			<Anchor>//api/name/infoWithResolution:currency:quantity:product:price:</Anchor>
            <NodeRef refid="9"/>
		</Token>
		
		<Token>
			<TokenIdentifier>//apple_ref/occ/instm/USMonetizationPurchaseInfo/initWithDictionaryRepresentation:</TokenIdentifier>
			<Abstract type="html">Designated initializer for restoring information object from its dictionary representation.</Abstract>
			<DeclaredIn>USMonetizationPurchaseInfo.h</DeclaredIn>
			
			<Declaration>- (instancetype)initWithDictionaryRepresentation:(NSDictionary *)aDictionary</Declaration>
			<Parameters>
				<Parameter>
					<Name>aDictionary</Name>
					<Abstract type="html">Dictionary representation of the receiver.</Abstract>
				</Parameter>
			</Parameters>
			
			<Anchor>//api/name/initWithDictionaryRepresentation:</Anchor>
            <NodeRef refid="9"/>
		</Token>
		
		<Token>
			<TokenIdentifier>//apple_ref/occ/instm/USMonetizationPurchaseInfo/setTotalPrice:</TokenIdentifier>
			<Abstract type="html">The total price of the transaction, including fractional amounts of the currency, before
store fees have been taken into account.</Abstract>
			<DeclaredIn>USMonetizationPurchaseInfo.h</DeclaredIn>
			
			<Declaration>@property (nonatomic, assign, readwrite) float totalPrice</Declaration>
			
			
			<Anchor>//api/name/totalPrice</Anchor>
            <NodeRef refid="9"/>
		</Token>
		
		<Token>
			<TokenIdentifier>//apple_ref/occ/instm/USMonetizationPurchaseInfo/totalPrice</TokenIdentifier>
			<Abstract type="html">The total price of the transaction, including fractional amounts of the currency, before
store fees have been taken into account.</Abstract>
			<DeclaredIn>USMonetizationPurchaseInfo.h</DeclaredIn>
			
			<Declaration>@property (nonatomic, assign, readwrite) float totalPrice</Declaration>
			
			
			<Anchor>//api/name/totalPrice</Anchor>
            <NodeRef refid="9"/>
		</Token>
		
		<Token>
			<TokenIdentifier>//apple_ref/occ/instp/USMonetizationPurchaseInfo/totalPrice</TokenIdentifier>
			<Abstract type="html">The total price of the transaction, including fractional amounts of the currency, before
store fees have been taken into account.</Abstract>
			<DeclaredIn>USMonetizationPurchaseInfo.h</DeclaredIn>
			
			<Declaration>@property (nonatomic, assign, readwrite) float totalPrice</Declaration>
			
			
			<Anchor>//api/name/totalPrice</Anchor>
            <NodeRef refid="9"/>
		</Token>
		
		<Token>
			<TokenIdentifier>//apple_ref/occ/instm/USMonetizationPurchaseInfo/setCurrency:</TokenIdentifier>
			<Abstract type="html">The currency as a 3-character ISO 4217 code.</Abstract>
			<DeclaredIn>USMonetizationPurchaseInfo.h</DeclaredIn>
			
			<Declaration>@property (nonatomic, strong, readwrite) NSString *currency</Declaration>
			
			
			<Anchor>//api/name/currency</Anchor>
            <NodeRef refid="9"/>
		</Token>
		
		<Token>
			<TokenIdentifier>//apple_ref/occ/instm/USMonetizationPurchaseInfo/currency</TokenIdentifier>
			<Abstract type="html">The currency as a 3-character ISO 4217 code.</Abstract>
			<DeclaredIn>USMonetizationPurchaseInfo.h</DeclaredIn>
			
			<Declaration>@property (nonatomic, strong, readwrite) NSString *currency</Declaration>
			
			
			<Anchor>//api/name/currency</Anchor>
            <NodeRef refid="9"/>
		</Token>
		
		<Token>
			<TokenIdentifier>//apple_ref/occ/instp/USMonetizationPurchaseInfo/currency</TokenIdentifier>
			<Abstract type="html">The currency as a 3-character ISO 4217 code.</Abstract>
			<DeclaredIn>USMonetizationPurchaseInfo.h</DeclaredIn>
			
			<Declaration>@property (nonatomic, strong, readwrite) NSString *currency</Declaration>
			
			
			<Anchor>//api/name/currency</Anchor>
            <NodeRef refid="9"/>
		</Token>
		
		<Token>
			<TokenIdentifier>//apple_ref/occ/instm/USMonetizationPurchaseInfo/setProduct:</TokenIdentifier>
			<Abstract type="html">Unique identifier of the product.</Abstract>
			<DeclaredIn>USMonetizationPurchaseInfo.h</DeclaredIn>
			
			<Declaration>@property (nonatomic, strong, readwrite) NSString *product</Declaration>
			
			
			<Anchor>//api/name/product</Anchor>
            <NodeRef refid="9"/>
		</Token>
		
		<Token>
			<TokenIdentifier>//apple_ref/occ/instm/USMonetizationPurchaseInfo/product</TokenIdentifier>
			<Abstract type="html">Unique identifier of the product.</Abstract>
			<DeclaredIn>USMonetizationPurchaseInfo.h</DeclaredIn>
			
			<Declaration>@property (nonatomic, strong, readwrite) NSString *product</Declaration>
			
			
			<Anchor>//api/name/product</Anchor>
            <NodeRef refid="9"/>
		</Token>
		
		<Token>
			<TokenIdentifier>//apple_ref/occ/instp/USMonetizationPurchaseInfo/product</TokenIdentifier>
			<Abstract type="html">Unique identifier of the product.</Abstract>
			<DeclaredIn>USMonetizationPurchaseInfo.h</DeclaredIn>
			
			<Declaration>@property (nonatomic, strong, readwrite) NSString *product</Declaration>
			
			
			<Anchor>//api/name/product</Anchor>
            <NodeRef refid="9"/>
		</Token>
		
        
        
	</File>
</Tokens>